pretalx_salesforce/__init__.py
pretalx_salesforce/apps.py
pretalx_salesforce/forms.py
pretalx_salesforce/models.py
pretalx_salesforce/signals.py
pretalx_salesforce/sync.py
pretalx_salesforce/tasks.py
pretalx_salesforce/urls.py
pretalx_salesforce/views.py
pretalx_salesforce/locale/django.pot
pretalx_salesforce/locale/ar/LC_MESSAGES/django.mo
pretalx_salesforce/locale/ar/LC_MESSAGES/django.po
pretalx_salesforce/locale/bg/LC_MESSAGES/django.mo
pretalx_salesforce/locale/bg/LC_MESSAGES/django.po
pretalx_salesforce/locale/ca/LC_MESSAGES/django.mo
pretalx_salesforce/locale/ca/LC_MESSAGES/django.po
pretalx_salesforce/locale/cs/LC_MESSAGES/django.mo
pretalx_salesforce/locale/cs/LC_MESSAGES/django.po
pretalx_salesforce/locale/de_DE/LC_MESSAGES/django.mo
pretalx_salesforce/locale/de_DE/LC_MESSAGES/django.po
pretalx_salesforce/locale/de_Formal/LC_MESSAGES/django.mo
pretalx_salesforce/locale/de_Formal/LC_MESSAGES/django.po
pretalx_salesforce/locale/el/LC_MESSAGES/django.mo
pretalx_salesforce/locale/el/LC_MESSAGES/django.po
pretalx_salesforce/locale/es/LC_MESSAGES/django.mo
pretalx_salesforce/locale/es/LC_MESSAGES/django.po
pretalx_salesforce/locale/es_MX/LC_MESSAGES/django.mo
pretalx_salesforce/locale/es_MX/LC_MESSAGES/django.po
pretalx_salesforce/locale/fr_FR/LC_MESSAGES/django.mo
pretalx_salesforce/locale/fr_FR/LC_MESSAGES/django.po
pretalx_salesforce/locale/id/LC_MESSAGES/django.mo
pretalx_salesforce/locale/id/LC_MESSAGES/django.po
pretalx_salesforce/locale/it/LC_MESSAGES/django.mo
pretalx_salesforce/locale/it/LC_MESSAGES/django.po
pretalx_salesforce/locale/ja_JP/LC_MESSAGES/django.mo
pretalx_salesforce/locale/ja_JP/LC_MESSAGES/django.po
pretalx_salesforce/locale/ko/LC_MESSAGES/django.mo
pretalx_salesforce/locale/ko/LC_MESSAGES/django.po
pretalx_salesforce/locale/nl/LC_MESSAGES/django.mo
pretalx_salesforce/locale/nl/LC_MESSAGES/django.po
pretalx_salesforce/locale/pl/LC_MESSAGES/django.mo
pretalx_salesforce/locale/pl/LC_MESSAGES/django.po
pretalx_salesforce-0.1.0.dist-info/licenses/LICENSE
pretalx_salesforce-0.1.0.dist-info/METADATA
pretalx_salesforce-0.1.0.dist-info/WHEEL
pretalx_salesforce-0.1.0.dist-info/entry_points.txt
pretalx_salesforce-0.1.0.dist-info/top_level.txt
pretalx_salesforce-0.1.0.dist-info/RECORD
