Metadata-Version: 2.4
Name: pretalx-salesforce
Version: 0.1.0
Summary: Send speaker and proposal information to SalesForce
Author-email: Tobias Kunze <r@rixx.de>
Maintainer-email: Tobias Kunze <r@rixx.de>
License: Apache Software License
Project-URL: homepage, https://github.com/pretalx/pretalx-salesforce
Project-URL: repository, https://github.com/pretalx/pretalx-salesforce.git
Keywords: pretalx
License-File: LICENSE
Requires-Dist: simple_salesforce
Dynamic: license-file
